wx_mcp_server_test/__init__.py
wx_mcp_server_test/server.py
wx_mcp_server_test-0.1.0.dist-info/METADATA
wx_mcp_server_test-0.1.0.dist-info/WHEEL
wx_mcp_server_test-0.1.0.dist-info/entry_points.txt
wx_mcp_server_test-0.1.0.dist-info/RECORD
